{
 "Shapes": [{"prefabShape":"Square","rotationZ":0.0,"level":20,"x":0.6000000238418579,"y":0.6000000238418579},{"prefabShape":"Triangle","rotationZ":0.0,"level":20,"x":0.6000000238418579,"y":1.2000000476837159},{"prefabShape":"Circle","rotationZ":0.0,"level":20,"x":0.4000000059604645,"y":0.4000000059604645},{"prefabShape":"Circle","rotationZ":0.0,"level":20,"x":0.4000000059604645,"y":0.4000000059604645},{"prefabShape":"Circle","rotationZ":0.0,"level":20,"x":0.4000000059604645,"y":0.4000000059604645},{"prefabShape":"Circle","rotationZ":0.0,"level":20,"x":0.4000000059604645,"y":0.4000000059604645},{"prefabShape":"Bar","rotationZ":0.0,"level":20,"x":1.0,"y":0.7},{"prefabShape":"Square","rotationZ":0.0,"level":20,"x":0.4000000059604645,"y":0.4000000059604645},{"prefabShape":"Square","rotationZ":0.0,"level":20,"x":0.4000000059604645,"y":0.4000000059604645},{"prefabShape":"Triangle","rotationZ":0.0,"level":20,"x":0.4000000059604645,"y":0.4000000059604645},{"prefabShape":"Triangle","rotationZ":0.0,"level":20,"x":0.4000000059604645,"y":0.4000000059604645},{"prefabShape":"Triangle","rotationZ":0.0,"level":20,"x":0.4000000059604645,"y":0.4000000059604645},{"prefabShape":"Triangle","rotationZ":180.0,"level":20,"x":0.4000000059604645,"y":0.4000000059604645},{"prefabShape":"Triangle","rotationZ":180.0,"level":20,"x":0.4000000059604645,"y":0.4000000059604645},{"prefabShape":"Square","rotationZ":180.0,"level":20,"x":0.4000000059604645,"y":0.4000000059604645},{"prefabShape":"Square","rotationZ":180.0,"level":20,"x":0.4000000059604645,"y":0.4000000059604645},{"prefabShape":"Circle","rotationZ":180.0,"level":20,"x":0.6000000238418579,"y":0.6000000238418579},
	]
"Platform": [{"shape":"2","posX":0.0,"posY":-3.0,"posZ":0.0,"rotX":0.0,"rotY":0.0,"rotZ":0.0,"scaleX":1.0,"scaleY":2.0,"scaleZ":1.0},{"shape":"3","posX":2.0,"posY":0.0,"posZ":0.0,"rotX":0.0,"rotY":0.0,"rotZ":10.000003814697266,"scaleX":0.6,"scaleY":0.8,"scaleZ":1.0},{"shape":"3","posX":-2.0,"posY":0.0,"posZ":0.0,"rotX":0.0,"rotY":0.0,"rotZ":350.0,"scaleX":0.6,"scaleY":0.8,"scaleZ":1.0},
	]
}